automatic_code_review_commons/__init__.py
automatic_code_review_commons/comment.py
automatic_code_review_commons/review.py
automatic_code_review_commons-1.0.5.dist-info/METADATA
automatic_code_review_commons-1.0.5.dist-info/WHEEL
automatic_code_review_commons-1.0.5.dist-info/top_level.txt
automatic_code_review_commons-1.0.5.dist-info/RECORD
