Metadata-Version: 2.1
Name: automatic-code-review-commons
Version: 1.0.5
Summary: Biblioteca com funções genéricas para revisões automáticas de código do projeto ACR
Home-page: https://github.com/automatic-code-review/automatic-code-review-commons
Author: Kielson Zinn da Silva
Author-email: automatic.code.review@gmail.com
License: UNKNOWN
Platform: UNKNOWN
Classifier: Programming Language :: Python :: 3
Classifier: License :: OSI Approved :: MIT License
Classifier: Operating System :: OS Independent
Requires-Python: >=3.6
